lms/__init__.py
lms/common/__init__.py
lms/common/lms_datatype.py
lms/common/lms_exceptions.py
lms/common/lms_fileinfo.py
lms/common/stream/fileinfo.py
lms/common/stream/hashtable.py
lms/common/stream/section.py
lms/fileio/encoding.py
lms/fileio/io.py
lms/message/__init__.py
lms/message/msbt.py
lms/message/msbtentry.py
lms/message/msbtio.py
lms/message/definitions/__init__.py
lms/message/definitions/lms_messagetext.py
lms/message/definitions/field/__init__.py
lms/message/definitions/field/io.py
lms/message/definitions/field/lms_field.py
lms/message/section/__init__.py
lms/message/section/atr1.py
lms/message/section/tsy1.py
lms/message/section/txt2.py
lms/message/tag/__init__.py
lms/message/tag/lms_tag.py
lms/message/tag/lms_tagexceptions.py
lms/message/tag/io/param_io.py
lms/message/tag/io/tag_io.py
lms/project/__init__.py
lms/project/msbp.py
lms/project/msbpread.py
lms/project/definitions/__init__.py
lms/project/definitions/attribute.py
lms/project/definitions/color.py
lms/project/definitions/style.py
lms/project/definitions/tag.py
lms/project/section/ali2.py
lms/project/section/ati2.py
lms/project/section/clr1.py
lms/project/section/string.py
lms/project/section/syl3.py
lms/project/section/tag2.py
lms/project/section/tgg2.py
lms/project/section/tgp2.py
lms/titleconfig/__init__.py
lms/titleconfig/config.py
lms/titleconfig/definitions/__init__.py
lms/titleconfig/definitions/attribute.py
lms/titleconfig/definitions/tags.py
lms/titleconfig/definitions/value.py
lms/titleconfig/presets/Badge Arcade.yaml
lms/titleconfig/presets/Brain Age Concentration Training.yaml
lms/titleconfig/presets/Kirby Planet Robobot.yaml
lms/titleconfig/presets/Super Mario 3D Land.yaml
lms/titleconfig/presets/Super Mario 3D World + Bowsers Fury.yaml
lms/titleconfig/presets/Super Mario Odyssey.yaml
lms/titleconfig/presets/The Legend of Zelda Echos of Wisdom.yaml
lms/titleconfig/presets/The Legend of Zelda a Link Between Worlds.yaml
lms/titleconfig/presets/Tomodachi Life.yaml
pylibms-3.2.4.dist-info/licenses/LICENSE
pylibms-3.2.4.dist-info/METADATA
pylibms-3.2.4.dist-info/WHEEL
pylibms-3.2.4.dist-info/top_level.txt
pylibms-3.2.4.dist-info/RECORD
