Metadata-Version: 2.4
Name: PyLibMS
Version: 3.2.4
Summary: Python library built for the libMessageStudio (LMS) proprietary file formats from Nintendo. Supports MSBT, MSBP, and MSBF.
Author: AbdyyEee
License: Copyright 2025 AbdyyEee
Project-URL: Documentation, https://github.com/AbdyyEee/PylibMS/wiki
Project-URL: Repository, https://github.com/AbdyyEee/PylibMS
Keywords: nintendo,msbf,msbt,msbp,modding,lms,libmessagestudio
Requires-Python: >=3.12
License-File: LICENSE
Requires-Dist: PyYAML>=6.0.1
Dynamic: license-file
